bayspec/__info__.py
bayspec/__init__.py
bayspec/data/__init__.py
bayspec/data/data.py
bayspec/data/response.py
bayspec/data/spectrum.py
bayspec/infer/__init__.py
bayspec/infer/infer.py
bayspec/infer/pair.py
bayspec/infer/posterior.py
bayspec/infer/statistic.py
bayspec/model/__init__.py
bayspec/model/model.py
bayspec/model/astro/__init__.py
bayspec/model/local/__init__.py
bayspec/model/local/additive.py
bayspec/model/local/mathematic.py
bayspec/model/local/multiplicative.py
bayspec/model/user/__init__.py
bayspec/model/user/user.py
bayspec/model/xspec/__init__.py
bayspec/util/__init__.py
bayspec/util/corner.py
bayspec/util/info.py
bayspec/util/param.py
bayspec/util/plot.py
bayspec/util/post.py
bayspec/util/prior.py
bayspec/util/significance.py
bayspec/util/tools.py
bayspec-0.3.6.dist-info/licenses/LICENSE
bayspec-0.3.6.dist-info/METADATA
bayspec-0.3.6.dist-info/WHEEL
bayspec-0.3.6.dist-info/top_level.txt
bayspec-0.3.6.dist-info/RECORD
